coffeeRequests/UA.json
coffeeRequests/__init__.py
coffeeRequests/_version.py
coffeeRequests/coffeeRequests.py
coffeeRequests/pool.py
coffeeRequests/proxy_pool.py
coffeeRequests/user_agent_pool.py
coffeeRequests/tests/__init__.py
coffeeRequests/tests/test_coffeeRequests.py
coffeeRequests/tests/test_proxy_pool.py
coffeeRequests/tests/test_user_agent_pool.py
coffeeRequests-0.0.5.dist-info/LICENSE
coffeeRequests-0.0.5.dist-info/METADATA
coffeeRequests-0.0.5.dist-info/WHEEL
coffeeRequests-0.0.5.dist-info/top_level.txt
coffeeRequests-0.0.5.dist-info/RECORD
