Metadata-Version: 2.1
Name: coffeeRequests
Version: 0.0.5
Summary: Tools for Economic Applications
Home-page: UNKNOWN
Author: chenjiahui
Author-email: chenjiahui1991@163.com
License: MIT Licence
Platform: UNKNOWN
